file_chooser/__init__.py
file_chooser/file_chooser.glade
file_chooser/file_chooser.glade~
file_chooser/file_chooser.py
gtk_file_chooser-0.2.0.dist-info/WHEEL
gtk_file_chooser-0.2.0.dist-info/METADATA
gtk_file_chooser-0.2.0.dist-info/RECORD
