Metadata-Version: 2.1
Name: gtk-file-chooser
Version: 0.2.0
Summary: A Simple Gtk File Chooser Dialog
License: GPL-3.0+
Author: BeatLink
Author-email: beatlink@protonmail.com
Requires-Python: >=3.6,<4.0
Classifier: License :: OSI Approved :: GNU General Public License v3 or later (GPLv3+)
Classifier: Programming Language :: Python :: 3
Classifier: Programming Language :: Python :: 3.6
Classifier: Programming Language :: Python :: 3.7
Requires-Dist: pygobject (>=3.32.2,<4.0.0)
